wildflow/__init__.py
wildflow-0.1.5.dist-info/METADATA
wildflow-0.1.5.dist-info/WHEEL
wildflow-0.1.5.dist-info/top_level.txt
wildflow-0.1.5.dist-info/RECORD
